cd_directory_manager/__init__.py
cd_directory_manager/directory_manager.py
cd_directory_manager/file_manager.py
cd_directory_manager/path_manager.py
cd_directory_manager/version.py
cd_directory_manager/zipper.py
cd_directory_manager-0.6.0.dist-info/LICENSE.md
cd_directory_manager-0.6.0.dist-info/LICENSE.txt
cd_directory_manager-0.6.0.dist-info/METADATA
cd_directory_manager-0.6.0.dist-info/WHEEL
cd_directory_manager-0.6.0.dist-info/RECORD
