Metadata-Version: 2.1
Name: cd-directory-manager
Version: 0.6.0
Summary: A package containing utilities for file and directory management, ZIP operations, and more.
License: MIT
Author: Nick Capasso
Author-email: codedocta@gmail.com
Requires-Python: >=3.9,<4.0
Classifier: License :: OSI Approved :: MIT License
Classifier: Programming Language :: Python :: 3
Classifier: Programming Language :: Python :: 3.9
Classifier: Programming Language :: Python :: 3.10
Classifier: Programming Language :: Python :: 3.11
Classifier: Programming Language :: Python :: 3.12
